extended_functools/__init__.py
extended_functools/py.typed
extended_functools/timeout.py
extended_functools-0.2.1.dist-info/METADATA
extended_functools-0.2.1.dist-info/WHEEL
extended_functools-0.2.1.dist-info/licenses/LICENSE
extended_functools-0.2.1.dist-info/RECORD
