Metadata-Version: 2.4
Name: extended-functools
Version: 0.2.1
Summary: Additional tools for functional programming in Python.
Project-URL: Homepage, https://pypi.org/project/extended-functools/
Project-URL: Repository, https://github.com/Diapolo10/extended-functools
Project-URL: Documentation, https://github.com/Diapolo10/extended-functools/tree/main/docs
Author-email: Lari Liuhamo <lari.liuhamo+pypi@gmail.com>
Maintainer-email: Lari Liuhamo <lari.liuhamo+pypi@gmail.com>
License: # MIT License
License-File: LICENSE
Keywords: python3
Classifier: Development Status :: 3 - Alpha
Classifier: License :: OSI Approved :: MIT License
Classifier: Operating System :: OS Independent
Classifier: Programming Language :: Python :: 3.10
Classifier: Programming Language :: Python :: 3.11
Classifier: Programming Language :: Python :: 3.12
Classifier: Programming Language :: Python :: 3.13
Classifier: Programming Language :: Python :: Implementation :: CPython
Classifier: Programming Language :: Python :: Implementation :: PyPy
Classifier: Typing :: Typed
Requires-Python: >=3.10
